{"id": "40JXmrRgkCKqZ7cTnRmgvi", "track_data": {"album": {"album_type": "album", "artists": [{"external_urls": {"spotify": "https://open.spotify.com/artist/5gs4Sm2WQUkcGeikMcVHbh"}, "href": "https://api.spotify.com/v1/artists/5gs4Sm2WQUkcGeikMcVHbh", "id": "5gs4Sm2WQUkcGeikMcVHbh", "name": "Hamza", "type": "artist", "uri": "spotify:artist:5gs4Sm2WQUkcGeikMcVHbh"}], "available_markets": ["AD", "AR", "AT", "AU", "BE", "BG", "BO", "BR", "CA", "CH", "CL", "CO", "CR", "CY", "CZ", "DE", "DK", "DO", "EC", "EE", "ES", "FI", "FR", "GB", "GR", "GT", "HK", "HN", "HU", "ID", "IE", "IL", "IS", "IT", "JP", "LI", "LT", "LU", "LV", "MC", "MT", "MX", "MY", "NI", "NL", "NO", "NZ", "PA", "PE", "PH", "PL", "PT", "PY", "RO", "SE", "SG", "SK", "SV", "TH", "TR", "TW", "US", "UY", "VN", "ZA"], "external_urls": {"spotify": "https://open.spotify.com/album/4zMhr0zJkbSVubSnKzD7UM"}, "href": "https://api.spotify.com/v1/albums/4zMhr0zJkbSVubSnKzD7UM", "id": "4zMhr0zJkbSVubSnKzD7UM", "images": [{"height": 640, "url": "https://i.scdn.co/image/8261afab2ea0f1dd35b40b159ff8dab6f8ceff86", "width": 640}, {"height": 300, "url": "https://i.scdn.co/image/b058164ea7c10eb58fe312891678f97c114e8592", "width": 300}, {"height": 64, "url": "https://i.scdn.co/image/c1993b59925657f7e2729a2b7d5b7c0f656f4300", "width": 64}], "name": "1994", "release_date": "2017-10-27", "release_date_precision": "day", "total_tracks": 14, "type": "album", "uri": "spotify:album:4zMhr0zJkbSVubSnKzD7UM"}, "artists": [{"external_urls": {"spotify": "https://open.spotify.com/artist/5gs4Sm2WQUkcGeikMcVHbh"}, "href": "https://api.spotify.com/v1/artists/5gs4Sm2WQUkcGeikMcVHbh", "id": "5gs4Sm2WQUkcGeikMcVHbh", "name": "Hamza", "type": "artist", "uri": "spotify:artist:5gs4Sm2WQUkcGeikMcVHbh"}], "available_markets": ["AD", "AR", "AT", "AU", "BE", "BG", "BO", "BR", "CA", "CH", "CL", "CO", "CR", "CY", "CZ", "DE", "DK", "DO", "EC", "EE", "ES", "FI", "FR", "GB", "GR", "GT", "HK", "HN", "HU", "ID", "IE", "IL", "IS", "IT", "JP", "LI", "LT", "LU", "LV", "MC", "MT", "MX", "MY", "NI", "NL", "NO", "NZ", "PA", "PE", "PH", "PL", "PT", "PY", "RO", "SE", "SG", "SK", "SV", "TH", "TR", "TW", "US", "UY", "VN", "ZA"], "disc_number": 1, "duration_ms": 233880, "explicit": true, "external_ids": {"isrc": "BE6GM1700001"}, "external_urls": {"spotify": "https://open.spotify.com/track/40JXmrRgkCKqZ7cTnRmgvi"}, "href": "https://api.spotify.com/v1/tracks/40JXmrRgkCKqZ7cTnRmgvi", "id": "40JXmrRgkCKqZ7cTnRmgvi", "is_local": false, "name": "Godzilla", "popularity": 48, "preview_url": "https://p.scdn.co/mp3-preview/bea7e3eb0985729166ade0f0b5f505d585dabf7a?cid=a36bb6a2df094ea981ce8977beab47df", "track_number": 7, "type": "track", "uri": "spotify:track:40JXmrRgkCKqZ7cTnRmgvi"}, "artist_data": [{"external_urls": {"spotify": "https://open.spotify.com/artist/5gs4Sm2WQUkcGeikMcVHbh"}, "href": "https://api.spotify.com/v1/artists/5gs4Sm2WQUkcGeikMcVHbh", "id": "5gs4Sm2WQUkcGeikMcVHbh", "name": "Hamza", "type": "artist", "uri": "spotify:artist:5gs4Sm2WQUkcGeikMcVHbh"}], "plays": 1}