{"id": "3kg6TBrDgA5Hu1aYXQZ5iN", "track_data": {"album": {"album_type": "single", "artists": [{"external_urls": {"spotify": "https://open.spotify.com/artist/5xW9faV2hqlLG0rp7CTBof"}, "href": "https://api.spotify.com/v1/artists/5xW9faV2hqlLG0rp7CTBof", "id": "5xW9faV2hqlLG0rp7CTBof", "name": "Julian le Play", "type": "artist", "uri": "spotify:artist:5xW9faV2hqlLG0rp7CTBof"}], "available_markets": ["AD", "AR", "AT", "AU", "BE", "BG", "BO", "BR", "CA", "CH", "CL", "CO", "CR", "CY", "CZ", "DE", "DK", "DO", "EC", "EE", "ES", "FI", "FR", "GB", "GR", "GT", "HK", "HN", "HU", "ID", "IE", "IL", "IS", "IT", "JP", "LI", "LT", "LU", "LV", "MC", "MT", "MX", "MY", "NI", "NL", "NO", "NZ", "PA", "PE", "PH", "PL", "PT", "PY", "RO", "SE", "SG", "SK", "SV", "TH", "TR", "TW", "US", "UY", "VN", "ZA"], "external_urls": {"spotify": "https://open.spotify.com/album/3QwSfPJPIarwI7FmvOoEB9"}, "href": "https://api.spotify.com/v1/albums/3QwSfPJPIarwI7FmvOoEB9", "id": "3QwSfPJPIarwI7FmvOoEB9", "images": [{"height": 640, "url": "https://i.scdn.co/image/edd89ce72f513c763159362f84c42f9b034962c1", "width": 640}, {"height": 300, "url": "https://i.scdn.co/image/84eba8412534ea9cd18fc3eef579ee1dc588c1cc", "width": 300}, {"height": 64, "url": "https://i.scdn.co/image/640af5f369f5de56b6a284479ef784e3c6b21aeb", "width": 64}], "name": "Rollercoaster", "release_date": "2014-07-04", "release_date_precision": "day", "total_tracks": 4, "type": "album", "uri": "spotify:album:3QwSfPJPIarwI7FmvOoEB9"}, "artists": [{"external_urls": {"spotify": "https://open.spotify.com/artist/5xW9faV2hqlLG0rp7CTBof"}, "href": "https://api.spotify.com/v1/artists/5xW9faV2hqlLG0rp7CTBof", "id": "5xW9faV2hqlLG0rp7CTBof", "name": "Julian le Play", "type": "artist", "uri": "spotify:artist:5xW9faV2hqlLG0rp7CTBof"}], "available_markets": ["AD", "AR", "AT", "AU", "BE", "BG", "BO", "BR", "CA", "CH", "CL", "CO", "CR", "CY", "CZ", "DE", "DK", "DO", "EC", "EE", "ES", "FI", "FR", "GB", "GR", "GT", "HK", "HN", "HU", "ID", "IE", "IL", "IS", "IT", "JP", "LI", "LT", "LU", "LV", "MC", "MT", "MX", "MY", "NI", "NL", "NO", "NZ", "PA", "PE", "PH", "PL", "PT", "PY", "RO", "SE", "SG", "SK", "SV", "TH", "TR", "TW", "US", "UY", "VN", "ZA"], "disc_number": 1, "duration_ms": 367986, "explicit": false, "external_ids": {"isrc": "DEL051420003"}, "external_urls": {"spotify": "https://open.spotify.com/track/3kg6TBrDgA5Hu1aYXQZ5iN"}, "href": "https://api.spotify.com/v1/tracks/3kg6TBrDgA5Hu1aYXQZ5iN", "id": "3kg6TBrDgA5Hu1aYXQZ5iN", "is_local": false, "name": "Rollercoaster - Remix filous", "popularity": 48, "preview_url": "https://p.scdn.co/mp3-preview/1a35280c2e4450b464bbe78560333dcd1c6178a5?cid=a36bb6a2df094ea981ce8977beab47df", "track_number": 3, "type": "track", "uri": "spotify:track:3kg6TBrDgA5Hu1aYXQZ5iN"}, "artist_data": [{"external_urls": {"spotify": "https://open.spotify.com/artist/5xW9faV2hqlLG0rp7CTBof"}, "href": "https://api.spotify.com/v1/artists/5xW9faV2hqlLG0rp7CTBof", "id": "5xW9faV2hqlLG0rp7CTBof", "name": "Julian le Play", "type": "artist", "uri": "spotify:artist:5xW9faV2hqlLG0rp7CTBof"}], "plays": 2}