{"id": "1LzNfuep1bnAUR9skqdHCK", "track_data": {"album": {"album_type": "album", "artists": [{"external_urls": {"spotify": "https://open.spotify.com/artist/37w38cCSGgKLdayTRjna4W"}, "href": "https://api.spotify.com/v1/artists/37w38cCSGgKLdayTRjna4W", "id": "37w38cCSGgKLdayTRjna4W", "name": "Mazzy Star", "type": "artist", "uri": "spotify:artist:37w38cCSGgKLdayTRjna4W"}], "available_markets": ["AD", "AR", "AT", "AU", "BE", "BG", "BO", "BR", "CA", "CH", "CL", "CO", "CR", "CY", "CZ", "DE", "DK", "DO", "EC", "EE", "ES", "FI", "FR", "GB", "GR", "GT", "HK", "HN", "HU", "ID", "IE", "IL", "IS", "IT", "JP", "LI", "LT", "LU", "LV", "MC", "MT", "MX", "MY", "NI", "NL", "NO", "NZ", "PA", "PE", "PH", "PL", "PT", "PY", "RO", "SE", "SG", "SK", "SV", "TH", "TR", "TW", "US", "UY", "VN", "ZA"], "external_urls": {"spotify": "https://open.spotify.com/album/5K18gTgac0q6Jma5HkV1vA"}, "href": "https://api.spotify.com/v1/albums/5K18gTgac0q6Jma5HkV1vA", "id": "5K18gTgac0q6Jma5HkV1vA", "images": [{"height": 640, "url": "https://i.scdn.co/image/e3382b3db6d87c7a2520d16db7d2665491914ca0", "width": 640}, {"height": 300, "url": "https://i.scdn.co/image/6f2cd8d2aa27ef04f808f2c0eb69327489061174", "width": 300}, {"height": 64, "url": "https://i.scdn.co/image/98b3a74025435da7ba959c44adfcad86f7e7b99d", "width": 64}], "name": "So Tonight That I Might See", "release_date": "1993-01-01", "release_date_precision": "day", "total_tracks": 10, "type": "album", "uri": "spotify:album:5K18gTgac0q6Jma5HkV1vA"}, "artists": [{"external_urls": {"spotify": "https://open.spotify.com/artist/37w38cCSGgKLdayTRjna4W"}, "href": "https://api.spotify.com/v1/artists/37w38cCSGgKLdayTRjna4W", "id": "37w38cCSGgKLdayTRjna4W", "name": "Mazzy Star", "type": "artist", "uri": "spotify:artist:37w38cCSGgKLdayTRjna4W"}], "available_markets": ["AD", "AR", "AT", "AU", "BE", "BG", "BO", "BR", "CA", "CH", "CL", "CO", "CR", "CY", "CZ", "DE", "DK", "DO", "EC", "EE", "ES", "FI", "FR", "GB", "GR", "GT", "HK", "HN", "HU", "ID", "IE", "IL", "IS", "IT", "JP", "LI", "LT", "LU", "LV", "MC", "MT", "MX", "MY", "NI", "NL", "NO", "NZ", "PA", "PE", "PH", "PL", "PT", "PY", "RO", "SE", "SG", "SK", "SV", "TH", "TR", "TW", "US", "UY", "VN", "ZA"], "disc_number": 1, "duration_ms": 295600, "explicit": false, "external_ids": {"isrc": "USCA29300105"}, "external_urls": {"spotify": "https://open.spotify.com/track/1LzNfuep1bnAUR9skqdHCK"}, "href": "https://api.spotify.com/v1/tracks/1LzNfuep1bnAUR9skqdHCK", "id": "1LzNfuep1bnAUR9skqdHCK", "is_local": false, "name": "Fade Into You", "popularity": 69, "preview_url": null, "track_number": 1, "type": "track", "uri": "spotify:track:1LzNfuep1bnAUR9skqdHCK"}, "artist_data": [{"external_urls": {"spotify": "https://open.spotify.com/artist/37w38cCSGgKLdayTRjna4W"}, "href": "https://api.spotify.com/v1/artists/37w38cCSGgKLdayTRjna4W", "id": "37w38cCSGgKLdayTRjna4W", "name": "Mazzy Star", "type": "artist", "uri": "spotify:artist:37w38cCSGgKLdayTRjna4W"}], "plays": 11}