{"id": "0n6ZG5eBT2R1g06QFkIL4W", "track_data": {"album": {"album_type": "album", "artists": [{"external_urls": {"spotify": "https://open.spotify.com/artist/7rB4hzbbTjvLPXwh6uVxPI"}, "href": "https://api.spotify.com/v1/artists/7rB4hzbbTjvLPXwh6uVxPI", "id": "7rB4hzbbTjvLPXwh6uVxPI", "name": "Backing Force", "type": "artist", "uri": "spotify:artist:7rB4hzbbTjvLPXwh6uVxPI"}], "available_markets": ["AD", "AR", "AT", "AU", "BE", "BG", "BO", "BR", "CA", "CH", "CL", "CO", "CR", "CY", "CZ", "DE", "DK", "DO", "EC", "EE", "ES", "FI", "FR", "GB", "GR", "GT", "HK", "HN", "HU", "ID", "IE", "IL", "IS", "IT", "JP", "LI", "LT", "LU", "LV", "MC", "MT", "MX", "MY", "NI", "NL", "NO", "NZ", "PA", "PE", "PH", "PL", "PT", "PY", "RO", "SE", "SG", "SK", "SV", "TH", "TR", "TW", "US", "UY", "VN", "ZA"], "external_urls": {"spotify": "https://open.spotify.com/album/1ez8WPgpk64PX0HqyleaMz"}, "href": "https://api.spotify.com/v1/albums/1ez8WPgpk64PX0HqyleaMz", "id": "1ez8WPgpk64PX0HqyleaMz", "images": [{"height": 640, "url": "https://i.scdn.co/image/d96031aaddee4ec5bc4d3e0586c3806ac9164832", "width": 640}, {"height": 300, "url": "https://i.scdn.co/image/c11eb35ddb1049fa2330cb180a2675292c46cd1a", "width": 300}, {"height": 64, "url": "https://i.scdn.co/image/1fee0ed607e47502219e0f037268569856e950d5", "width": 64}], "name": "Euro Karaoke Hit Mix - 2014 - Vol. 8", "release_date": "2014-12-16", "release_date_precision": "day", "total_tracks": 15, "type": "album", "uri": "spotify:album:1ez8WPgpk64PX0HqyleaMz"}, "artists": [{"external_urls": {"spotify": "https://open.spotify.com/artist/7rB4hzbbTjvLPXwh6uVxPI"}, "href": "https://api.spotify.com/v1/artists/7rB4hzbbTjvLPXwh6uVxPI", "id": "7rB4hzbbTjvLPXwh6uVxPI", "name": "Backing Force", "type": "artist", "uri": "spotify:artist:7rB4hzbbTjvLPXwh6uVxPI"}], "available_markets": ["AD", "AR", "AT", "AU", "BE", "BG", "BO", "BR", "CA", "CH", "CL", "CO", "CR", "CY", "CZ", "DE", "DK", "DO", "EC", "EE", "ES", "FI", "FR", "GB", "GR", "GT", "HK", "HN", "HU", "ID", "IE", "IL", "IS", "IT", "JP", "LI", "LT", "LU", "LV", "MC", "MT", "MX", "MY", "NI", "NL", "NO", "NZ", "PA", "PE", "PH", "PL", "PT", "PY", "RO", "SE", "SG", "SK", "SV", "TH", "TR", "TW", "US", "UY", "VN", "ZA"], "disc_number": 1, "duration_ms": 259805, "explicit": false, "external_ids": {"isrc": "NLAX61288802"}, "external_urls": {"spotify": "https://open.spotify.com/track/0n6ZG5eBT2R1g06QFkIL4W"}, "href": "https://api.spotify.com/v1/tracks/0n6ZG5eBT2R1g06QFkIL4W", "id": "0n6ZG5eBT2R1g06QFkIL4W", "is_local": false, "name": "Latch (Originally Performed by Disclosure feat. Sam Smith) [Karaoke Version]", "popularity": 1, "preview_url": "https://p.scdn.co/mp3-preview/8a27bb3a188fc3dd808e3a8d983963b5a94ba79a?cid=a36bb6a2df094ea981ce8977beab47df", "track_number": 12, "type": "track", "uri": "spotify:track:0n6ZG5eBT2R1g06QFkIL4W"}, "artist_data": [{"external_urls": {"spotify": "https://open.spotify.com/artist/7rB4hzbbTjvLPXwh6uVxPI"}, "href": "https://api.spotify.com/v1/artists/7rB4hzbbTjvLPXwh6uVxPI", "id": "7rB4hzbbTjvLPXwh6uVxPI", "name": "Backing Force", "type": "artist", "uri": "spotify:artist:7rB4hzbbTjvLPXwh6uVxPI"}], "plays": 2}