{"id": "6f5i916F3jU6BhOOD7iGqf", "track_data": {"album": {"album_type": "single", "artists": [{"external_urls": {"spotify": "https://open.spotify.com/artist/5SyGEPymt1G2uto47tVWvZ"}, "href": "https://api.spotify.com/v1/artists/5SyGEPymt1G2uto47tVWvZ", "id": "5SyGEPymt1G2uto47tVWvZ", "name": "MadeinTYO", "type": "artist", "uri": "spotify:artist:5SyGEPymt1G2uto47tVWvZ"}, {"external_urls": {"spotify": "https://open.spotify.com/artist/5dHt1vcEm9qb8fCyLcB3HL"}, "href": "https://api.spotify.com/v1/artists/5dHt1vcEm9qb8fCyLcB3HL", "id": "5dHt1vcEm9qb8fCyLcB3HL", "name": "A$AP Ferg", "type": "artist", "uri": "spotify:artist:5dHt1vcEm9qb8fCyLcB3HL"}], "available_markets": ["AD", "AR", "AT", "AU", "BE", "BG", "BO", "BR", "CA", "CH", "CL", "CO", "CR", "CY", "CZ", "DE", "DK", "DO", "EC", "EE", "ES", "FI", "FR", "GB", "GR", "GT", "HK", "HN", "HU", "ID", "IE", "IL", "IS", "IT", "JP", "LI", "LT", "LU", "LV", "MC", "MT", "MX", "MY", "NI", "NL", "NO", "NZ", "PA", "PE", "PH", "PL", "PT", "PY", "RO", "SE", "SG", "SK", "SV", "TH", "TR", "TW", "US", "UY", "VN", "ZA"], "external_urls": {"spotify": "https://open.spotify.com/album/6ype8Ax1cvN5DBqBKBVAkw"}, "href": "https://api.spotify.com/v1/albums/6ype8Ax1cvN5DBqBKBVAkw", "id": "6ype8Ax1cvN5DBqBKBVAkw", "images": [{"height": 640, "url": "https://i.scdn.co/image/a5af879480aa85ffe7b29ca448114435b93e1538", "width": 640}, {"height": 300, "url": "https://i.scdn.co/image/47d8711dcc548e711fade621c2a367fa9de3163e", "width": 300}, {"height": 64, "url": "https://i.scdn.co/image/20708a324ad069949870da96cf60e219657bde0e", "width": 64}], "name": "Ned Flanders (feat. A$AP Ferg)", "release_date": "2018-05-31", "release_date_precision": "day", "total_tracks": 1, "type": "album", "uri": "spotify:album:6ype8Ax1cvN5DBqBKBVAkw"}, "artists": [{"external_urls": {"spotify": "https://open.spotify.com/artist/5SyGEPymt1G2uto47tVWvZ"}, "href": "https://api.spotify.com/v1/artists/5SyGEPymt1G2uto47tVWvZ", "id": "5SyGEPymt1G2uto47tVWvZ", "name": "MadeinTYO", "type": "artist", "uri": "spotify:artist:5SyGEPymt1G2uto47tVWvZ"}, {"external_urls": {"spotify": "https://open.spotify.com/artist/5dHt1vcEm9qb8fCyLcB3HL"}, "href": "https://api.spotify.com/v1/artists/5dHt1vcEm9qb8fCyLcB3HL", "id": "5dHt1vcEm9qb8fCyLcB3HL", "name": "A$AP Ferg", "type": "artist", "uri": "spotify:artist:5dHt1vcEm9qb8fCyLcB3HL"}], "available_markets": ["AD", "AR", "AT", "AU", "BE", "BG", "BO", "BR", "CA", "CH", "CL", "CO", "CR", "CY", "CZ", "DE", "DK", "DO", "EC", "EE", "ES", "FI", "FR", "GB", "GR", "GT", "HK", "HN", "HU", "ID", "IE", "IL", "IS", "IT", "JP", "LI", "LT", "LU", "LV", "MC", "MT", "MX", "MY", "NI", "NL", "NO", "NZ", "PA", "PE", "PH", "PL", "PT", "PY", "RO", "SE", "SG", "SK", "SV", "TH", "TR", "TW", "US", "UY", "VN", "ZA"], "disc_number": 1, "duration_ms": 161013, "explicit": true, "external_ids": {"isrc": "QMRSZ1800848"}, "external_urls": {"spotify": "https://open.spotify.com/track/6f5i916F3jU6BhOOD7iGqf"}, "href": "https://api.spotify.com/v1/tracks/6f5i916F3jU6BhOOD7iGqf", "id": "6f5i916F3jU6BhOOD7iGqf", "is_local": false, "name": "Ned Flanders (feat. A$AP Ferg)", "popularity": 82, "preview_url": "https://p.scdn.co/mp3-preview/a2d3fb76b958249755e7099e2e73a87666f2f627?cid=a36bb6a2df094ea981ce8977beab47df", "track_number": 1, "type": "track", "uri": "spotify:track:6f5i916F3jU6BhOOD7iGqf"}, "artist_data": [{"external_urls": {"spotify": "https://open.spotify.com/artist/5SyGEPymt1G2uto47tVWvZ"}, "href": "https://api.spotify.com/v1/artists/5SyGEPymt1G2uto47tVWvZ", "id": "5SyGEPymt1G2uto47tVWvZ", "name": "MadeinTYO", "type": "artist", "uri": "spotify:artist:5SyGEPymt1G2uto47tVWvZ"}, {"external_urls": {"spotify": "https://open.spotify.com/artist/5dHt1vcEm9qb8fCyLcB3HL"}, "href": "https://api.spotify.com/v1/artists/5dHt1vcEm9qb8fCyLcB3HL", "id": "5dHt1vcEm9qb8fCyLcB3HL", "name": "A$AP Ferg", "type": "artist", "uri": "spotify:artist:5dHt1vcEm9qb8fCyLcB3HL"}], "plays": 2}