{"id": "41tuX4nCMkniFG0K1z9QzR", "track_data": {"album": {"album_type": "single", "artists": [{"external_urls": {"spotify": "https://open.spotify.com/artist/7GaMopkesD4KK9dNbgyO5D"}, "href": "https://api.spotify.com/v1/artists/7GaMopkesD4KK9dNbgyO5D", "id": "7GaMopkesD4KK9dNbgyO5D", "name": "Eko Fresh", "type": "artist", "uri": "spotify:artist:7GaMopkesD4KK9dNbgyO5D"}], "available_markets": ["AD", "AR", "AT", "AU", "BE", "BG", "BO", "BR", "CA", "CH", "CL", "CO", "CR", "CY", "CZ", "DE", "DK", "DO", "EC", "EE", "ES", "FI", "FR", "GB", "GR", "GT", "HK", "HN", "HU", "ID", "IE", "IL", "IS", "IT", "JP", "LI", "LT", "LU", "LV", "MC", "MT", "MX", "MY", "NI", "NL", "NO", "NZ", "PA", "PE", "PH", "PL", "PT", "PY", "RO", "SE", "SG", "SK", "SV", "TH", "TR", "TW", "US", "UY", "VN", "ZA"], "external_urls": {"spotify": "https://open.spotify.com/album/4eIH8JsIILekAseNheWdZd"}, "href": "https://api.spotify.com/v1/albums/4eIH8JsIILekAseNheWdZd", "id": "4eIH8JsIILekAseNheWdZd", "images": [{"height": 589, "url": "https://i.scdn.co/image/c7974f3ba79acd9456ce86f46e976cd266d27966", "width": 640}, {"height": 276, "url": "https://i.scdn.co/image/f70e5c3482326654359382e69316efc5c61b087e", "width": 300}, {"height": 59, "url": "https://i.scdn.co/image/751eb1ab512181e5985180941c7db8dadeee69a5", "width": 64}], "name": "K\u00f6nig von Deutschland", "release_date": "2003-07-07", "release_date_precision": "day", "total_tracks": 4, "type": "album", "uri": "spotify:album:4eIH8JsIILekAseNheWdZd"}, "artists": [{"external_urls": {"spotify": "https://open.spotify.com/artist/7GaMopkesD4KK9dNbgyO5D"}, "href": "https://api.spotify.com/v1/artists/7GaMopkesD4KK9dNbgyO5D", "id": "7GaMopkesD4KK9dNbgyO5D", "name": "Eko Fresh", "type": "artist", "uri": "spotify:artist:7GaMopkesD4KK9dNbgyO5D"}], "available_markets": ["AD", "AR", "AT", "AU", "BE", "BG", "BO", "BR", "CA", "CH", "CL", "CO", "CR", "CY", "CZ", "DE", "DK", "DO", "EC", "EE", "ES", "FI", "FR", "GB", "GR", "GT", "HK", "HN", "HU", "ID", "IE", "IL", "IS", "IT", "JP", "LI", "LT", "LU", "LV", "MC", "MT", "MX", "MY", "NI", "NL", "NO", "NZ", "PA", "PE", "PH", "PL", "PT", "PY", "RO", "SE", "SG", "SK", "SV", "TH", "TR", "TW", "US", "UY", "VN", "ZA"], "disc_number": 1, "duration_ms": 195160, "explicit": false, "external_ids": {"isrc": "DEA810300436"}, "external_urls": {"spotify": "https://open.spotify.com/track/41tuX4nCMkniFG0K1z9QzR"}, "href": "https://api.spotify.com/v1/tracks/41tuX4nCMkniFG0K1z9QzR", "id": "41tuX4nCMkniFG0K1z9QzR", "is_local": false, "name": "Heat", "popularity": 2, "preview_url": "https://p.scdn.co/mp3-preview/9699d8d7e27d013f04218c714c3062308dc08fe4?cid=a36bb6a2df094ea981ce8977beab47df", "track_number": 3, "type": "track", "uri": "spotify:track:41tuX4nCMkniFG0K1z9QzR"}, "artist_data": [{"external_urls": {"spotify": "https://open.spotify.com/artist/7GaMopkesD4KK9dNbgyO5D"}, "href": "https://api.spotify.com/v1/artists/7GaMopkesD4KK9dNbgyO5D", "id": "7GaMopkesD4KK9dNbgyO5D", "name": "Eko Fresh", "type": "artist", "uri": "spotify:artist:7GaMopkesD4KK9dNbgyO5D"}], "plays": 1}