{"id": "1U5tKsz4uXnvZzH1xYCSio", "track_data": {"album": {"album_type": "album", "artists": [{"external_urls": {"spotify": "https://open.spotify.com/artist/6X8WdFjrNhXATMDSs26aCc"}, "href": "https://api.spotify.com/v1/artists/6X8WdFjrNhXATMDSs26aCc", "id": "6X8WdFjrNhXATMDSs26aCc", "name": "Curren$y", "type": "artist", "uri": "spotify:artist:6X8WdFjrNhXATMDSs26aCc"}], "available_markets": ["AD", "AR", "AT", "AU", "BE", "BG", "BO", "BR", "CA", "CH", "CL", "CO", "CR", "CY", "CZ", "DE", "DK", "DO", "EC", "EE", "ES", "FI", "FR", "GB", "GR", "GT", "HK", "HN", "HU", "ID", "IE", "IL", "IS", "IT", "JP", "LI", "LT", "LU", "LV", "MC", "MT", "MX", "MY", "NI", "NL", "NO", "NZ", "PA", "PE", "PH", "PL", "PT", "PY", "RO", "SE", "SG", "SK", "SV", "TH", "TR", "TW", "US", "UY", "VN", "ZA"], "external_urls": {"spotify": "https://open.spotify.com/album/487wwLDg5ECDKr1n5mi21q"}, "href": "https://api.spotify.com/v1/albums/487wwLDg5ECDKr1n5mi21q", "id": "487wwLDg5ECDKr1n5mi21q", "images": [{"height": 640, "url": "https://i.scdn.co/image/16aad460a961ec00c46c872c1e0c37f79fe07aa5", "width": 640}, {"height": 300, "url": "https://i.scdn.co/image/def2219d8d40ea7c2a55c311427c71889c124a58", "width": 300}, {"height": 64, "url": "https://i.scdn.co/image/c4c7add7c0db6f6e05eebd70e476c4a8467f4dc2", "width": 64}], "name": "Weekend At Burnie's (Deluxe Version)", "release_date": "2011-06-24", "release_date_precision": "day", "total_tracks": 12, "type": "album", "uri": "spotify:album:487wwLDg5ECDKr1n5mi21q"}, "artists": [{"external_urls": {"spotify": "https://open.spotify.com/artist/6X8WdFjrNhXATMDSs26aCc"}, "href": "https://api.spotify.com/v1/artists/6X8WdFjrNhXATMDSs26aCc", "id": "6X8WdFjrNhXATMDSs26aCc", "name": "Curren$y", "type": "artist", "uri": "spotify:artist:6X8WdFjrNhXATMDSs26aCc"}], "available_markets": ["AD", "AR", "AT", "AU", "BE", "BG", "BO", "BR", "CA", "CH", "CL", "CO", "CR", "CY", "CZ", "DE", "DK", "DO", "EC", "EE", "ES", "FI", "FR", "GB", "GR", "GT", "HK", "HN", "HU", "ID", "IE", "IL", "IS", "IT", "JP", "LI", "LT", "LU", "LV", "MC", "MT", "MX", "MY", "NI", "NL", "NO", "NZ", "PA", "PE", "PH", "PL", "PT", "PY", "RO", "SE", "SG", "SK", "SV", "TH", "TR", "TW", "US", "UY", "VN", "ZA"], "disc_number": 1, "duration_ms": 271653, "explicit": true, "external_ids": {"isrc": "USWB11101288"}, "external_urls": {"spotify": "https://open.spotify.com/track/1U5tKsz4uXnvZzH1xYCSio"}, "href": "https://api.spotify.com/v1/tracks/1U5tKsz4uXnvZzH1xYCSio", "id": "1U5tKsz4uXnvZzH1xYCSio", "is_local": false, "name": "She Don't Want A Man", "popularity": 41, "preview_url": "https://p.scdn.co/mp3-preview/d56e9d6a218bcb1fa1d45da0e89422706c49bd82?cid=a36bb6a2df094ea981ce8977beab47df", "track_number": 3, "type": "track", "uri": "spotify:track:1U5tKsz4uXnvZzH1xYCSio"}, "artist_data": [{"external_urls": {"spotify": "https://open.spotify.com/artist/6X8WdFjrNhXATMDSs26aCc"}, "href": "https://api.spotify.com/v1/artists/6X8WdFjrNhXATMDSs26aCc", "id": "6X8WdFjrNhXATMDSs26aCc", "name": "Curren$y", "type": "artist", "uri": "spotify:artist:6X8WdFjrNhXATMDSs26aCc"}], "plays": 1}