{"id": "6YS1MXqso0zlmcL4OV1kXk", "track_data": {"album": {"album_type": "album", "artists": [{"external_urls": {"spotify": "https://open.spotify.com/artist/7HS5tD2CPw2AgG4AgWpxpN"}, "href": "https://api.spotify.com/v1/artists/7HS5tD2CPw2AgG4AgWpxpN", "id": "7HS5tD2CPw2AgG4AgWpxpN", "name": "M\u00e9lanie Laurent", "type": "artist", "uri": "spotify:artist:7HS5tD2CPw2AgG4AgWpxpN"}], "available_markets": ["AD", "AR", "AT", "AU", "BE", "BG", "BO", "BR", "CA", "CH", "CL", "CO", "CR", "CY", "CZ", "DE", "DK", "DO", "EC", "EE", "ES", "FI", "FR", "GB", "GR", "GT", "HK", "HN", "HU", "ID", "IE", "IL", "IS", "IT", "JP", "LI", "LT", "LU", "LV", "MC", "MT", "MX", "MY", "NI", "NL", "NO", "NZ", "PA", "PE", "PH", "PL", "PT", "PY", "RO", "SE", "SG", "SK", "SV", "TH", "TR", "TW", "US", "UY", "VN", "ZA"], "external_urls": {"spotify": "https://open.spotify.com/album/4zojkjd8EnxhvBQAx1Nd4W"}, "href": "https://api.spotify.com/v1/albums/4zojkjd8EnxhvBQAx1Nd4W", "id": "4zojkjd8EnxhvBQAx1Nd4W", "images": [{"height": 640, "url": "https://i.scdn.co/image/25ba067a603bb512de85409496cfcd04d7a12357", "width": 640}, {"height": 300, "url": "https://i.scdn.co/image/3a5e9affc29b2fce969c851e5e8933f036a92697", "width": 300}, {"height": 64, "url": "https://i.scdn.co/image/c9e83bf921ed407d18a66d297824c39008a4b70a", "width": 64}], "name": "En t'attendant", "release_date": "2011-05-02", "release_date_precision": "day", "total_tracks": 12, "type": "album", "uri": "spotify:album:4zojkjd8EnxhvBQAx1Nd4W"}, "artists": [{"external_urls": {"spotify": "https://open.spotify.com/artist/7HS5tD2CPw2AgG4AgWpxpN"}, "href": "https://api.spotify.com/v1/artists/7HS5tD2CPw2AgG4AgWpxpN", "id": "7HS5tD2CPw2AgG4AgWpxpN", "name": "M\u00e9lanie Laurent", "type": "artist", "uri": "spotify:artist:7HS5tD2CPw2AgG4AgWpxpN"}], "available_markets": ["AD", "AR", "AT", "AU", "BE", "BG", "BO", "BR", "CA", "CH", "CL", "CO", "CR", "CY", "CZ", "DE", "DK", "DO", "EC", "EE", "ES", "FI", "FR", "GB", "GR", "GT", "HK", "HN", "HU", "ID", "IE", "IL", "IS", "IT", "JP", "LI", "LT", "LU", "LV", "MC", "MT", "MX", "MY", "NI", "NL", "NO", "NZ", "PA", "PE", "PH", "PL", "PT", "PY", "RO", "SE", "SG", "SK", "SV", "TH", "TR", "TW", "US", "UY", "VN", "ZA"], "disc_number": 1, "duration_ms": 160066, "explicit": false, "external_ids": {"isrc": "FRPBE1000010"}, "external_urls": {"spotify": "https://open.spotify.com/track/6YS1MXqso0zlmcL4OV1kXk"}, "href": "https://api.spotify.com/v1/tracks/6YS1MXqso0zlmcL4OV1kXk", "id": "6YS1MXqso0zlmcL4OV1kXk", "is_local": false, "name": "D\u00e9but", "popularity": 72, "preview_url": "https://p.scdn.co/mp3-preview/2003873bae46055c98ecb3b2e7b8b5e9bcd9842c?cid=a36bb6a2df094ea981ce8977beab47df", "track_number": 1, "type": "track", "uri": "spotify:track:6YS1MXqso0zlmcL4OV1kXk"}, "artist_data": [{"external_urls": {"spotify": "https://open.spotify.com/artist/7HS5tD2CPw2AgG4AgWpxpN"}, "href": "https://api.spotify.com/v1/artists/7HS5tD2CPw2AgG4AgWpxpN", "id": "7HS5tD2CPw2AgG4AgWpxpN", "name": "M\u00e9lanie Laurent", "type": "artist", "uri": "spotify:artist:7HS5tD2CPw2AgG4AgWpxpN"}], "plays": 18}