{"id": "0E4WMwQL4Obxs3b7NqH4Td", "track_data": {"album": {"album_type": "album", "artists": [{"external_urls": {"spotify": "https://open.spotify.com/artist/49vCIUW46QY3L5vo1xVFoy"}, "href": "https://api.spotify.com/v1/artists/49vCIUW46QY3L5vo1xVFoy", "id": "49vCIUW46QY3L5vo1xVFoy", "name": "Trae Tha Truth", "type": "artist", "uri": "spotify:artist:49vCIUW46QY3L5vo1xVFoy"}], "available_markets": ["AD", "AR", "AT", "AU", "BE", "BG", "BO", "BR", "CA", "CH", "CL", "CO", "CR", "CY", "CZ", "DE", "DK", "DO", "EC", "EE", "ES", "FI", "FR", "GB", "GR", "GT", "HK", "HN", "HU", "ID", "IE", "IL", "IS", "IT", "JP", "LI", "LT", "LU", "LV", "MC", "MT", "MX", "MY", "NI", "NL", "NO", "NZ", "PA", "PE", "PH", "PL", "PT", "PY", "RO", "SE", "SG", "SK", "SV", "TH", "TR", "TW", "US", "UY", "VN", "ZA"], "external_urls": {"spotify": "https://open.spotify.com/album/6WDf55WUYWJsC1hop6I7bX"}, "href": "https://api.spotify.com/v1/albums/6WDf55WUYWJsC1hop6I7bX", "id": "6WDf55WUYWJsC1hop6I7bX", "images": [{"height": 640, "url": "https://i.scdn.co/image/f78afdadfb53e284752808579bfa6154c58e54fd", "width": 640}, {"height": 300, "url": "https://i.scdn.co/image/f5a058cce9fd0f72f0fc9950f377419983110046", "width": 300}, {"height": 64, "url": "https://i.scdn.co/image/081139f3130176c6c6cfa90febc3b5ec27944477", "width": 64}], "name": "Tha Truth, Pt. 2", "release_date": "2016-02-05", "release_date_precision": "day", "total_tracks": 17, "type": "album", "uri": "spotify:album:6WDf55WUYWJsC1hop6I7bX"}, "artists": [{"external_urls": {"spotify": "https://open.spotify.com/artist/49vCIUW46QY3L5vo1xVFoy"}, "href": "https://api.spotify.com/v1/artists/49vCIUW46QY3L5vo1xVFoy", "id": "49vCIUW46QY3L5vo1xVFoy", "name": "Trae Tha Truth", "type": "artist", "uri": "spotify:artist:49vCIUW46QY3L5vo1xVFoy"}], "available_markets": ["AD", "AR", "AT", "AU", "BE", "BG", "BO", "BR", "CA", "CH", "CL", "CO", "CR", "CY", "CZ", "DE", "DK", "DO", "EC", "EE", "ES", "FI", "FR", "GB", "GR", "GT", "HK", "HN", "HU", "ID", "IE", "IL", "IS", "IT", "JP", "LI", "LT", "LU", "LV", "MC", "MT", "MX", "MY", "NI", "NL", "NO", "NZ", "PA", "PE", "PH", "PL", "PT", "PY", "RO", "SE", "SG", "SK", "SV", "TH", "TR", "TW", "US", "UY", "VN", "ZA"], "disc_number": 1, "duration_ms": 258086, "explicit": false, "external_ids": {"isrc": "USUYG1091114"}, "external_urls": {"spotify": "https://open.spotify.com/track/0E4WMwQL4Obxs3b7NqH4Td"}, "href": "https://api.spotify.com/v1/tracks/0E4WMwQL4Obxs3b7NqH4Td", "id": "0E4WMwQL4Obxs3b7NqH4Td", "is_local": false, "name": "I Will Survive", "popularity": 5, "preview_url": "https://p.scdn.co/mp3-preview/2be2edbbae27f1aa6e1e56270c104cc493ea8d0b?cid=a36bb6a2df094ea981ce8977beab47df", "track_number": 17, "type": "track", "uri": "spotify:track:0E4WMwQL4Obxs3b7NqH4Td"}, "artist_data": [{"external_urls": {"spotify": "https://open.spotify.com/artist/49vCIUW46QY3L5vo1xVFoy"}, "href": "https://api.spotify.com/v1/artists/49vCIUW46QY3L5vo1xVFoy", "id": "49vCIUW46QY3L5vo1xVFoy", "name": "Trae Tha Truth", "type": "artist", "uri": "spotify:artist:49vCIUW46QY3L5vo1xVFoy"}], "plays": 6}