{"id": "4WfiaD5XGwOSZ4etGdRyM0", "track_data": {"album": {"album_type": "single", "artists": [{"external_urls": {"spotify": "https://open.spotify.com/artist/1laJd6GKa8ersMhOuHZ22o"}, "href": "https://api.spotify.com/v1/artists/1laJd6GKa8ersMhOuHZ22o", "id": "1laJd6GKa8ersMhOuHZ22o", "name": "Jusa Dementor", "type": "artist", "uri": "spotify:artist:1laJd6GKa8ersMhOuHZ22o"}], "available_markets": ["AD", "AR", "AT", "AU", "BE", "BG", "BO", "BR", "CA", "CH", "CL", "CO", "CR", "CY", "CZ", "DE", "DK", "DO", "EC", "EE", "ES", "FI", "FR", "GB", "GR", "GT", "HK", "HN", "HU", "ID", "IE", "IL", "IS", "IT", "JP", "LI", "LT", "LU", "LV", "MC", "MT", "MX", "MY", "NI", "NL", "NO", "NZ", "PA", "PE", "PH", "PL", "PT", "PY", "RO", "SE", "SG", "SK", "SV", "TH", "TR", "TW", "US", "UY", "VN", "ZA"], "external_urls": {"spotify": "https://open.spotify.com/album/1sXSQwP4cB6GKYGkdLW21X"}, "href": "https://api.spotify.com/v1/albums/1sXSQwP4cB6GKYGkdLW21X", "id": "1sXSQwP4cB6GKYGkdLW21X", "images": [{"height": 640, "url": "https://i.scdn.co/image/e9d454d01e780db72e6226d2729f8d0ff821009a", "width": 640}, {"height": 300, "url": "https://i.scdn.co/image/2694284eb7d2a71d820a0180c31aa79fdb637389", "width": 300}, {"height": 64, "url": "https://i.scdn.co/image/d6d763a49a2cf79ae37b91b73b3da24da0c1be46", "width": 64}], "name": "My Spirit", "release_date": "2013-09-17", "release_date_precision": "day", "total_tracks": 1, "type": "album", "uri": "spotify:album:1sXSQwP4cB6GKYGkdLW21X"}, "artists": [{"external_urls": {"spotify": "https://open.spotify.com/artist/1laJd6GKa8ersMhOuHZ22o"}, "href": "https://api.spotify.com/v1/artists/1laJd6GKa8ersMhOuHZ22o", "id": "1laJd6GKa8ersMhOuHZ22o", "name": "Jusa Dementor", "type": "artist", "uri": "spotify:artist:1laJd6GKa8ersMhOuHZ22o"}], "available_markets": ["AD", "AR", "AT", "AU", "BE", "BG", "BO", "BR", "CA", "CH", "CL", "CO", "CR", "CY", "CZ", "DE", "DK", "DO", "EC", "EE", "ES", "FI", "FR", "GB", "GR", "GT", "HK", "HN", "HU", "ID", "IE", "IL", "IS", "IT", "JP", "LI", "LT", "LU", "LV", "MC", "MT", "MX", "MY", "NI", "NL", "NO", "NZ", "PA", "PE", "PH", "PL", "PT", "PY", "RO", "SE", "SG", "SK", "SV", "TH", "TR", "TW", "US", "UY", "VN", "ZA"], "disc_number": 1, "duration_ms": 435401, "explicit": false, "external_ids": {"isrc": "GBWUL1349778"}, "external_urls": {"spotify": "https://open.spotify.com/track/4WfiaD5XGwOSZ4etGdRyM0"}, "href": "https://api.spotify.com/v1/tracks/4WfiaD5XGwOSZ4etGdRyM0", "id": "4WfiaD5XGwOSZ4etGdRyM0", "is_local": false, "name": "My Spirit - Original mix", "popularity": 9, "preview_url": "https://p.scdn.co/mp3-preview/61358cb6037e42c73e5af125c42365fbb8147b14?cid=a36bb6a2df094ea981ce8977beab47df", "track_number": 1, "type": "track", "uri": "spotify:track:4WfiaD5XGwOSZ4etGdRyM0"}, "artist_data": [{"external_urls": {"spotify": "https://open.spotify.com/artist/1laJd6GKa8ersMhOuHZ22o"}, "href": "https://api.spotify.com/v1/artists/1laJd6GKa8ersMhOuHZ22o", "id": "1laJd6GKa8ersMhOuHZ22o", "name": "Jusa Dementor", "type": "artist", "uri": "spotify:artist:1laJd6GKa8ersMhOuHZ22o"}], "plays": 1}