{"id": "7dJs62WZCYMHDplPnQfVkd", "track_data": {"album": {"album_type": "album", "artists": [{"external_urls": {"spotify": "https://open.spotify.com/artist/00FQb4jTyendYWaN8pK0wa"}, "href": "https://api.spotify.com/v1/artists/00FQb4jTyendYWaN8pK0wa", "id": "00FQb4jTyendYWaN8pK0wa", "name": "Lana Del Rey", "type": "artist", "uri": "spotify:artist:00FQb4jTyendYWaN8pK0wa"}], "available_markets": ["AD", "AR", "AT", "AU", "BE", "BG", "BO", "BR", "CA", "CH", "CL", "CO", "CR", "CY", "CZ", "DE", "DK", "DO", "EC", "EE", "ES", "FI", "FR", "GB", "GR", "GT", "HK", "HN", "HU", "ID", "IE", "IL", "IS", "IT", "JP", "LI", "LT", "LU", "LV", "MC", "MT", "MX", "MY", "NI", "NL", "NO", "NZ", "PA", "PE", "PH", "PL", "PT", "PY", "RO", "SE", "SG", "SK", "SV", "TH", "TR", "TW", "US", "UY", "VN", "ZA"], "external_urls": {"spotify": "https://open.spotify.com/album/78KtSyGocoTvmcgw1lUHp4"}, "href": "https://api.spotify.com/v1/albums/78KtSyGocoTvmcgw1lUHp4", "id": "78KtSyGocoTvmcgw1lUHp4", "images": [{"height": 640, "url": "https://i.scdn.co/image/6b71bffef1ec948a6f76fbd2616b3c6ec7f74a85", "width": 640}, {"height": 300, "url": "https://i.scdn.co/image/f71979eb4ed4f6a53ba6198875feb01523b3940d", "width": 300}, {"height": 64, "url": "https://i.scdn.co/image/6e1f687c839d0214739e0d1d3b0121d7285c19f8", "width": 64}], "name": "Ultraviolence", "release_date": "2014-01-01", "release_date_precision": "day", "total_tracks": 15, "type": "album", "uri": "spotify:album:78KtSyGocoTvmcgw1lUHp4"}, "artists": [{"external_urls": {"spotify": "https://open.spotify.com/artist/00FQb4jTyendYWaN8pK0wa"}, "href": "https://api.spotify.com/v1/artists/00FQb4jTyendYWaN8pK0wa", "id": "00FQb4jTyendYWaN8pK0wa", "name": "Lana Del Rey", "type": "artist", "uri": "spotify:artist:00FQb4jTyendYWaN8pK0wa"}], "available_markets": ["AD", "AR", "AT", "AU", "BE", "BG", "BO", "BR", "CA", "CH", "CL", "CO", "CR", "CY", "CZ", "DE", "DK", "DO", "EC", "EE", "ES", "FI", "FR", "GB", "GR", "GT", "HK", "HN", "HU", "ID", "IE", "IL", "IS", "IT", "JP", "LI", "LT", "LU", "LV", "MC", "MT", "MX", "MY", "NI", "NL", "NO", "NZ", "PA", "PE", "PH", "PL", "PT", "PY", "RO", "SE", "SG", "SK", "SV", "TH", "TR", "TW", "US", "UY", "VN", "ZA"], "disc_number": 1, "duration_ms": 399092, "explicit": true, "external_ids": {"isrc": "GBUM71402167"}, "external_urls": {"spotify": "https://open.spotify.com/track/7dJs62WZCYMHDplPnQfVkd"}, "href": "https://api.spotify.com/v1/tracks/7dJs62WZCYMHDplPnQfVkd", "id": "7dJs62WZCYMHDplPnQfVkd", "is_local": false, "name": "Cruel World", "popularity": 34, "preview_url": null, "track_number": 1, "type": "track", "uri": "spotify:track:7dJs62WZCYMHDplPnQfVkd"}, "artist_data": [{"external_urls": {"spotify": "https://open.spotify.com/artist/00FQb4jTyendYWaN8pK0wa"}, "href": "https://api.spotify.com/v1/artists/00FQb4jTyendYWaN8pK0wa", "id": "00FQb4jTyendYWaN8pK0wa", "name": "Lana Del Rey", "type": "artist", "uri": "spotify:artist:00FQb4jTyendYWaN8pK0wa"}], "plays": 2}