{"id": "09UTQS7zNS7yHcEjExIj5N", "track_data": {"album": {"album_type": "album", "artists": [{"external_urls": {"spotify": "https://open.spotify.com/artist/0vWJnrBCvPOS7aBgXsBS2q"}, "href": "https://api.spotify.com/v1/artists/0vWJnrBCvPOS7aBgXsBS2q", "id": "0vWJnrBCvPOS7aBgXsBS2q", "name": "Friday Night At The Movies", "type": "artist", "uri": "spotify:artist:0vWJnrBCvPOS7aBgXsBS2q"}], "available_markets": ["AD", "AR", "AT", "AU", "BE", "BG", "BO", "BR", "CA", "CH", "CL", "CO", "CR", "CY", "CZ", "DE", "DK", "DO", "EC", "EE", "ES", "FI", "FR", "GB", "GR", "GT", "HK", "HN", "HU", "ID", "IE", "IL", "IS", "IT", "JP", "LI", "LT", "LU", "LV", "MC", "MT", "MX", "MY", "NI", "NL", "NO", "NZ", "PA", "PE", "PH", "PL", "PT", "PY", "RO", "SE", "SG", "SK", "SV", "TH", "TR", "TW", "US", "UY", "VN", "ZA"], "external_urls": {"spotify": "https://open.spotify.com/album/40iZK0IznkOIWsk3oQaPLa"}, "href": "https://api.spotify.com/v1/albums/40iZK0IznkOIWsk3oQaPLa", "id": "40iZK0IznkOIWsk3oQaPLa", "images": [{"height": 640, "url": "https://i.scdn.co/image/8c4c9ed5f2a9e186c4351c606a41e97c22a9d1cc", "width": 640}, {"height": 300, "url": "https://i.scdn.co/image/2d4f61fa6678b89506e2bcba567af583dfc85b2a", "width": 300}, {"height": 64, "url": "https://i.scdn.co/image/b83b0db780c2092fec90a3681be530297d7a882e", "width": 64}], "name": "Music From: Control, Shine A Light & Nowhere Boy", "release_date": "2010-07-27", "release_date_precision": "day", "total_tracks": 14, "type": "album", "uri": "spotify:album:40iZK0IznkOIWsk3oQaPLa"}, "artists": [{"external_urls": {"spotify": "https://open.spotify.com/artist/0vWJnrBCvPOS7aBgXsBS2q"}, "href": "https://api.spotify.com/v1/artists/0vWJnrBCvPOS7aBgXsBS2q", "id": "0vWJnrBCvPOS7aBgXsBS2q", "name": "Friday Night At The Movies", "type": "artist", "uri": "spotify:artist:0vWJnrBCvPOS7aBgXsBS2q"}], "available_markets": ["AD", "AR", "AT", "AU", "BE", "BG", "BO", "BR", "CA", "CH", "CL", "CO", "CR", "CY", "CZ", "DE", "DK", "DO", "EC", "EE", "ES", "FI", "FR", "GB", "GR", "GT", "HK", "HN", "HU", "ID", "IE", "IL", "IS", "IT", "JP", "LI", "LT", "LU", "LV", "MC", "MT", "MX", "MY", "NI", "NL", "NO", "NZ", "PA", "PE", "PH", "PL", "PT", "PY", "RO", "SE", "SG", "SK", "SV", "TH", "TR", "TW", "US", "UY", "VN", "ZA"], "disc_number": 1, "duration_ms": 155960, "explicit": false, "external_ids": {"isrc": "GBQRF0814611"}, "external_urls": {"spotify": "https://open.spotify.com/track/09UTQS7zNS7yHcEjExIj5N"}, "href": "https://api.spotify.com/v1/tracks/09UTQS7zNS7yHcEjExIj5N", "id": "09UTQS7zNS7yHcEjExIj5N", "is_local": false, "name": "Money (That's What I Want) - (From 'Nowhere Boy')", "popularity": 0, "preview_url": "https://p.scdn.co/mp3-preview/9a5b7a85cfc7166cf25f7377a679fc471d293acb?cid=a36bb6a2df094ea981ce8977beab47df", "track_number": 9, "type": "track", "uri": "spotify:track:09UTQS7zNS7yHcEjExIj5N"}, "artist_data": [{"external_urls": {"spotify": "https://open.spotify.com/artist/0vWJnrBCvPOS7aBgXsBS2q"}, "href": "https://api.spotify.com/v1/artists/0vWJnrBCvPOS7aBgXsBS2q", "id": "0vWJnrBCvPOS7aBgXsBS2q", "name": "Friday Night At The Movies", "type": "artist", "uri": "spotify:artist:0vWJnrBCvPOS7aBgXsBS2q"}], "plays": 6}