{"id": "0Kojfmpnf0A2yC1zyv39Zx", "track_data": {"album": {"album_type": "album", "artists": [{"external_urls": {"spotify": "https://open.spotify.com/artist/4xRYI6VqpkE3UwrDrAZL8L"}, "href": "https://api.spotify.com/v1/artists/4xRYI6VqpkE3UwrDrAZL8L", "id": "4xRYI6VqpkE3UwrDrAZL8L", "name": "Logic", "type": "artist", "uri": "spotify:artist:4xRYI6VqpkE3UwrDrAZL8L"}], "available_markets": ["AD", "AR", "AT", "AU", "BE", "BG", "BO", "BR", "CA", "CH", "CL", "CO", "CR", "CY", "CZ", "DE", "DK", "DO", "EC", "EE", "ES", "FI", "FR", "GB", "GR", "GT", "HK", "HN", "HU", "ID", "IE", "IL", "IS", "IT", "JP", "LI", "LT", "LU", "LV", "MC", "MT", "MX", "MY", "NI", "NL", "NO", "NZ", "PA", "PE", "PH", "PL", "PT", "PY", "RO", "SE", "SG", "SK", "SV", "TH", "TR", "TW", "US", "UY", "VN", "ZA"], "external_urls": {"spotify": "https://open.spotify.com/album/1Mk7Lei0Ra3hawezqmad5V"}, "href": "https://api.spotify.com/v1/albums/1Mk7Lei0Ra3hawezqmad5V", "id": "1Mk7Lei0Ra3hawezqmad5V", "images": [{"height": 640, "url": "https://i.scdn.co/image/eb3752f897c83b42a4c66512466b2d0652e54aa3", "width": 640}, {"height": 300, "url": "https://i.scdn.co/image/99dea35960970c3272e0ea5a5d5eb5e882820d93", "width": 300}, {"height": 64, "url": "https://i.scdn.co/image/e561c243a985bbe3f25c01f755d574420ce964c3", "width": 64}], "name": "Under Pressure (Deluxe)", "release_date": "2014-10-21", "release_date_precision": "day", "total_tracks": 15, "type": "album", "uri": "spotify:album:1Mk7Lei0Ra3hawezqmad5V"}, "artists": [{"external_urls": {"spotify": "https://open.spotify.com/artist/4xRYI6VqpkE3UwrDrAZL8L"}, "href": "https://api.spotify.com/v1/artists/4xRYI6VqpkE3UwrDrAZL8L", "id": "4xRYI6VqpkE3UwrDrAZL8L", "name": "Logic", "type": "artist", "uri": "spotify:artist:4xRYI6VqpkE3UwrDrAZL8L"}], "available_markets": ["AD", "AR", "AT", "AU", "BE", "BG", "BO", "BR", "CA", "CH", "CL", "CO", "CR", "CY", "CZ", "DE", "DK", "DO", "EC", "EE", "ES", "FI", "FR", "GB", "GR", "GT", "HK", "HN", "HU", "ID", "IE", "IL", "IS", "IT", "JP", "LI", "LT", "LU", "LV", "MC", "MT", "MX", "MY", "NI", "NL", "NO", "NZ", "PA", "PE", "PH", "PL", "PT", "PY", "RO", "SE", "SG", "SK", "SV", "TH", "TR", "TW", "US", "UY", "VN", "ZA"], "disc_number": 1, "duration_ms": 337746, "explicit": true, "external_ids": {"isrc": "USUM71414218"}, "external_urls": {"spotify": "https://open.spotify.com/track/0Kojfmpnf0A2yC1zyv39Zx"}, "href": "https://api.spotify.com/v1/tracks/0Kojfmpnf0A2yC1zyv39Zx", "id": "0Kojfmpnf0A2yC1zyv39Zx", "is_local": false, "name": "Buried Alive", "popularity": 61, "preview_url": null, "track_number": 5, "type": "track", "uri": "spotify:track:0Kojfmpnf0A2yC1zyv39Zx"}, "artist_data": [{"external_urls": {"spotify": "https://open.spotify.com/artist/4xRYI6VqpkE3UwrDrAZL8L"}, "href": "https://api.spotify.com/v1/artists/4xRYI6VqpkE3UwrDrAZL8L", "id": "4xRYI6VqpkE3UwrDrAZL8L", "name": "Logic", "type": "artist", "uri": "spotify:artist:4xRYI6VqpkE3UwrDrAZL8L"}], "plays": 1}