{"id": "2hmKfef7VYK8efH6ok5SP7", "track_data": {"album": {"album_type": "album", "artists": [{"external_urls": {"spotify": "https://open.spotify.com/artist/55Aa2cqylxrFIXC767Z865"}, "href": "https://api.spotify.com/v1/artists/55Aa2cqylxrFIXC767Z865", "id": "55Aa2cqylxrFIXC767Z865", "name": "Lil Wayne", "type": "artist", "uri": "spotify:artist:55Aa2cqylxrFIXC767Z865"}], "available_markets": ["AD", "AR", "AT", "AU", "BE", "BG", "BO", "BR", "CA", "CH", "CL", "CO", "CR", "CY", "CZ", "DE", "DK", "DO", "EC", "EE", "ES", "FI", "FR", "GB", "GR", "GT", "HK", "HN", "HU", "ID", "IE", "IL", "IS", "IT", "JP", "LI", "LT", "LU", "LV", "MC", "MT", "MX", "MY", "NI", "NL", "NO", "NZ", "PA", "PE", "PH", "PL", "PT", "PY", "RO", "SE", "SG", "SK", "SV", "TH", "TR", "TW", "US", "UY", "VN", "ZA"], "external_urls": {"spotify": "https://open.spotify.com/album/7oc6i8xUILaWwQ5BJMZS3c"}, "href": "https://api.spotify.com/v1/albums/7oc6i8xUILaWwQ5BJMZS3c", "id": "7oc6i8xUILaWwQ5BJMZS3c", "images": [{"height": 640, "url": "https://i.scdn.co/image/c49b2b9a3948ee0b78153a9ccad7c7f82002751c", "width": 640}, {"height": 300, "url": "https://i.scdn.co/image/22e6e91acac715168d555626738c84f707f96206", "width": 300}, {"height": 64, "url": "https://i.scdn.co/image/c180718d20a21a78186506b5917f28e48821360a", "width": 64}], "name": "Tha Carter IV (Deluxe)", "release_date": "2011-01-01", "release_date_precision": "day", "total_tracks": 18, "type": "album", "uri": "spotify:album:7oc6i8xUILaWwQ5BJMZS3c"}, "artists": [{"external_urls": {"spotify": "https://open.spotify.com/artist/55Aa2cqylxrFIXC767Z865"}, "href": "https://api.spotify.com/v1/artists/55Aa2cqylxrFIXC767Z865", "id": "55Aa2cqylxrFIXC767Z865", "name": "Lil Wayne", "type": "artist", "uri": "spotify:artist:55Aa2cqylxrFIXC767Z865"}], "available_markets": ["AD", "AR", "AT", "AU", "BE", "BG", "BO", "BR", "CA", "CH", "CL", "CO", "CR", "CY", "CZ", "DE", "DK", "DO", "EC", "EE", "ES", "FI", "FR", "GB", "GR", "GT", "HK", "HN", "HU", "ID", "IE", "IL", "IS", "IT", "JP", "LI", "LT", "LU", "LV", "MC", "MT", "MX", "MY", "NI", "NL", "NO", "NZ", "PA", "PE", "PH", "PL", "PT", "PY", "RO", "SE", "SG", "SK", "SV", "TH", "TR", "TW", "US", "UY", "VN", "ZA"], "disc_number": 1, "duration_ms": 172053, "explicit": true, "external_ids": {"isrc": "USCM51100301"}, "external_urls": {"spotify": "https://open.spotify.com/track/2hmKfef7VYK8efH6ok5SP7"}, "href": "https://api.spotify.com/v1/tracks/2hmKfef7VYK8efH6ok5SP7", "id": "2hmKfef7VYK8efH6ok5SP7", "is_local": false, "name": "Intro", "popularity": 41, "preview_url": null, "track_number": 1, "type": "track", "uri": "spotify:track:2hmKfef7VYK8efH6ok5SP7"}, "artist_data": [{"external_urls": {"spotify": "https://open.spotify.com/artist/55Aa2cqylxrFIXC767Z865"}, "href": "https://api.spotify.com/v1/artists/55Aa2cqylxrFIXC767Z865", "id": "55Aa2cqylxrFIXC767Z865", "name": "Lil Wayne", "type": "artist", "uri": "spotify:artist:55Aa2cqylxrFIXC767Z865"}], "plays": 3}