{"id": "4UYrVcOhdVQ2L0ZwYliXNH", "track_data": {"album": {"album_type": "album", "artists": [{"external_urls": {"spotify": "https://open.spotify.com/artist/0uhNYfjHJyAmHh2xNZ4vqf"}, "href": "https://api.spotify.com/v1/artists/0uhNYfjHJyAmHh2xNZ4vqf", "id": "0uhNYfjHJyAmHh2xNZ4vqf", "name": "Oxide & Neutrino", "type": "artist", "uri": "spotify:artist:0uhNYfjHJyAmHh2xNZ4vqf"}], "available_markets": ["AD", "AR", "AT", "AU", "BE", "BG", "BO", "BR", "CA", "CH", "CL", "CO", "CR", "CY", "CZ", "DE", "DK", "DO", "EC", "EE", "ES", "FI", "FR", "GB", "GR", "GT", "HK", "HN", "HU", "ID", "IE", "IL", "IS", "IT", "JP", "LI", "LT", "LU", "LV", "MC", "MT", "MX", "MY", "NI", "NL", "NO", "NZ", "PA", "PE", "PH", "PL", "PT", "PY", "RO", "SE", "SG", "SK", "SV", "TH", "TR", "TW", "US", "UY", "VN", "ZA"], "external_urls": {"spotify": "https://open.spotify.com/album/6FZCuZTkHljeaz5kli8WC8"}, "href": "https://api.spotify.com/v1/albums/6FZCuZTkHljeaz5kli8WC8", "id": "6FZCuZTkHljeaz5kli8WC8", "images": [{"height": 632, "url": "https://i.scdn.co/image/7a41cfe9e166479ba97991df6c07785ad946650e", "width": 640}, {"height": 296, "url": "https://i.scdn.co/image/6fee32239ca7cc142467ac7a7486df8d1889ed8b", "width": 300}, {"height": 63, "url": "https://i.scdn.co/image/83374bbc92758da93dda5c50070908e10c03bc0f", "width": 64}], "name": "Execute", "release_date": "2000-12-01", "release_date_precision": "day", "total_tracks": 26, "type": "album", "uri": "spotify:album:6FZCuZTkHljeaz5kli8WC8"}, "artists": [{"external_urls": {"spotify": "https://open.spotify.com/artist/0uhNYfjHJyAmHh2xNZ4vqf"}, "href": "https://api.spotify.com/v1/artists/0uhNYfjHJyAmHh2xNZ4vqf", "id": "0uhNYfjHJyAmHh2xNZ4vqf", "name": "Oxide & Neutrino", "type": "artist", "uri": "spotify:artist:0uhNYfjHJyAmHh2xNZ4vqf"}], "available_markets": ["AD", "AR", "AT", "AU", "BE", "BG", "BO", "BR", "CA", "CH", "CL", "CO", "CR", "CY", "CZ", "DE", "DK", "DO", "EC", "EE", "ES", "FI", "FR", "GB", "GR", "GT", "HK", "HN", "HU", "ID", "IE", "IL", "IS", "IT", "JP", "LI", "LT", "LU", "LV", "MC", "MT", "MX", "MY", "NI", "NL", "NO", "NZ", "PA", "PE", "PH", "PL", "PT", "PY", "RO", "SE", "SG", "SK", "SV", "TH", "TR", "TW", "US", "UY", "VN", "ZA"], "disc_number": 1, "duration_ms": 292226, "explicit": false, "external_ids": {"isrc": "GBAHS0004163"}, "external_urls": {"spotify": "https://open.spotify.com/track/4UYrVcOhdVQ2L0ZwYliXNH"}, "href": "https://api.spotify.com/v1/tracks/4UYrVcOhdVQ2L0ZwYliXNH", "id": "4UYrVcOhdVQ2L0ZwYliXNH", "is_local": false, "name": "Bound 4 Da Reload - Casualty", "popularity": 44, "preview_url": "https://p.scdn.co/mp3-preview/5b1e22f7bb2add7d7d2e04b4071a5b6442831cc8?cid=a36bb6a2df094ea981ce8977beab47df", "track_number": 7, "type": "track", "uri": "spotify:track:4UYrVcOhdVQ2L0ZwYliXNH"}, "artist_data": [{"external_urls": {"spotify": "https://open.spotify.com/artist/0uhNYfjHJyAmHh2xNZ4vqf"}, "href": "https://api.spotify.com/v1/artists/0uhNYfjHJyAmHh2xNZ4vqf", "id": "0uhNYfjHJyAmHh2xNZ4vqf", "name": "Oxide & Neutrino", "type": "artist", "uri": "spotify:artist:0uhNYfjHJyAmHh2xNZ4vqf"}], "plays": 1}