{"id": "22pzlAb4SynBW4aO0HCwo1", "track_data": {"album": {"album_type": "album", "artists": [{"external_urls": {"spotify": "https://open.spotify.com/artist/22xRIphSN7IkPVbErICu7s"}, "href": "https://api.spotify.com/v1/artists/22xRIphSN7IkPVbErICu7s", "id": "22xRIphSN7IkPVbErICu7s", "name": "Rob Dougan", "type": "artist", "uri": "spotify:artist:22xRIphSN7IkPVbErICu7s"}], "available_markets": ["AD", "AR", "AT", "AU", "BE", "BG", "BO", "BR", "CA", "CH", "CL", "CO", "CR", "CY", "CZ", "DE", "DK", "DO", "EC", "EE", "ES", "FI", "FR", "GB", "GR", "GT", "HK", "HN", "HU", "ID", "IE", "IL", "IS", "IT", "JP", "LI", "LT", "LU", "LV", "MC", "MT", "MX", "MY", "NI", "NL", "NO", "NZ", "PA", "PE", "PH", "PL", "PT", "PY", "RO", "SE", "SG", "SK", "SV", "TH", "TR", "TW", "US", "UY", "VN", "ZA"], "external_urls": {"spotify": "https://open.spotify.com/album/62dNwStZgn5XA2sZuMQ46F"}, "href": "https://api.spotify.com/v1/albums/62dNwStZgn5XA2sZuMQ46F", "id": "62dNwStZgn5XA2sZuMQ46F", "images": [{"height": 640, "url": "https://i.scdn.co/image/2bf3dab55987ba5bf8d03c49eeb9ee3fc3752959", "width": 640}, {"height": 300, "url": "https://i.scdn.co/image/559af50181ed42ff392161ef126047d5908006fb", "width": 300}, {"height": 64, "url": "https://i.scdn.co/image/f5277121858c5bc9004ee2e589162d163a66efc7", "width": 64}], "name": "Furious Angels (Vocal + Instrumental)", "release_date": "2001", "release_date_precision": "year", "total_tracks": 22, "type": "album", "uri": "spotify:album:62dNwStZgn5XA2sZuMQ46F"}, "artists": [{"external_urls": {"spotify": "https://open.spotify.com/artist/22xRIphSN7IkPVbErICu7s"}, "href": "https://api.spotify.com/v1/artists/22xRIphSN7IkPVbErICu7s", "id": "22xRIphSN7IkPVbErICu7s", "name": "Rob Dougan", "type": "artist", "uri": "spotify:artist:22xRIphSN7IkPVbErICu7s"}], "available_markets": ["AD", "AR", "AT", "AU", "BE", "BG", "BO", "BR", "CA", "CH", "CL", "CO", "CR", "CY", "CZ", "DE", "DK", "DO", "EC", "EE", "ES", "FI", "FR", "GB", "GR", "GT", "HK", "HN", "HU", "ID", "IE", "IL", "IS", "IT", "JP", "LI", "LT", "LU", "LV", "MC", "MT", "MX", "MY", "NI", "NL", "NO", "NZ", "PA", "PE", "PH", "PL", "PT", "PY", "RO", "SE", "SG", "SK", "SV", "TH", "TR", "TW", "US", "UY", "VN", "ZA"], "disc_number": 1, "duration_ms": 319960, "explicit": false, "external_ids": {"isrc": "GBBXH0100131"}, "external_urls": {"spotify": "https://open.spotify.com/track/22pzlAb4SynBW4aO0HCwo1"}, "href": "https://api.spotify.com/v1/tracks/22pzlAb4SynBW4aO0HCwo1", "id": "22pzlAb4SynBW4aO0HCwo1", "is_local": false, "name": "Born Yesterday", "popularity": 23, "preview_url": "https://p.scdn.co/mp3-preview/835b06b8750dec8afd24a1a574ede52016130675?cid=a36bb6a2df094ea981ce8977beab47df", "track_number": 9, "type": "track", "uri": "spotify:track:22pzlAb4SynBW4aO0HCwo1"}, "artist_data": [{"external_urls": {"spotify": "https://open.spotify.com/artist/22xRIphSN7IkPVbErICu7s"}, "href": "https://api.spotify.com/v1/artists/22xRIphSN7IkPVbErICu7s", "id": "22xRIphSN7IkPVbErICu7s", "name": "Rob Dougan", "type": "artist", "uri": "spotify:artist:22xRIphSN7IkPVbErICu7s"}], "plays": 1}