{"id": "2V5e8ubNeF9i24Uy1jaDLP", "track_data": {"album": {"album_type": "album", "artists": [{"external_urls": {"spotify": "https://open.spotify.com/artist/3JoDcjZtpq0ccldFgYmeAB"}, "href": "https://api.spotify.com/v1/artists/3JoDcjZtpq0ccldFgYmeAB", "id": "3JoDcjZtpq0ccldFgYmeAB", "name": "Party Tyme Karaoke", "type": "artist", "uri": "spotify:artist:3JoDcjZtpq0ccldFgYmeAB"}], "available_markets": ["AD", "AR", "AT", "AU", "BE", "BG", "BO", "BR", "CA", "CH", "CL", "CO", "CR", "CY", "CZ", "DE", "DK", "DO", "EC", "EE", "ES", "FI", "FR", "GB", "GR", "GT", "HK", "HN", "HU", "ID", "IE", "IL", "IS", "IT", "JP", "LI", "LT", "LU", "LV", "MC", "MT", "MX", "MY", "NI", "NL", "NO", "NZ", "PA", "PE", "PH", "PL", "PT", "PY", "RO", "SE", "SG", "SK", "SV", "TH", "TR", "TW", "US", "UY", "VN", "ZA"], "external_urls": {"spotify": "https://open.spotify.com/album/5MruCJ2OgwSxQytrfcn6Ui"}, "href": "https://api.spotify.com/v1/albums/5MruCJ2OgwSxQytrfcn6Ui", "id": "5MruCJ2OgwSxQytrfcn6Ui", "images": [{"height": 640, "url": "https://i.scdn.co/image/493f34810c845d36ba1579a5fb151e729b5cc5ff", "width": 640}, {"height": 300, "url": "https://i.scdn.co/image/027d2791eef40e821838ad864c96b01152f6ff3e", "width": 300}, {"height": 64, "url": "https://i.scdn.co/image/a5631bacb035174ddb7ce8050a4f8bdb71171869", "width": 64}], "name": "Party Tyme Karaoke - Hip Hop & Rap Hits 1", "release_date": "2018-09-07", "release_date_precision": "day", "total_tracks": 100, "type": "album", "uri": "spotify:album:5MruCJ2OgwSxQytrfcn6Ui"}, "artists": [{"external_urls": {"spotify": "https://open.spotify.com/artist/3JoDcjZtpq0ccldFgYmeAB"}, "href": "https://api.spotify.com/v1/artists/3JoDcjZtpq0ccldFgYmeAB", "id": "3JoDcjZtpq0ccldFgYmeAB", "name": "Party Tyme Karaoke", "type": "artist", "uri": "spotify:artist:3JoDcjZtpq0ccldFgYmeAB"}], "available_markets": ["AD", "AR", "AT", "AU", "BE", "BG", "BO", "BR", "CA", "CH", "CL", "CO", "CR", "CY", "CZ", "DE", "DK", "DO", "EC", "EE", "ES", "FI", "FR", "GB", "GR", "GT", "HK", "HN", "HU", "ID", "IE", "IL", "IS", "IT", "JP", "LI", "LT", "LU", "LV", "MC", "MT", "MX", "MY", "NI", "NL", "NO", "NZ", "PA", "PE", "PH", "PL", "PT", "PY", "RO", "SE", "SG", "SK", "SV", "TH", "TR", "TW", "US", "UY", "VN", "ZA"], "disc_number": 4, "duration_ms": 278413, "explicit": false, "external_ids": {"isrc": "USSYS1023793"}, "external_urls": {"spotify": "https://open.spotify.com/track/2V5e8ubNeF9i24Uy1jaDLP"}, "href": "https://api.spotify.com/v1/tracks/2V5e8ubNeF9i24Uy1jaDLP", "id": "2V5e8ubNeF9i24Uy1jaDLP", "is_local": false, "name": "Live Your Life (Made Popular By T.I. ft. Rihanna) [Karaoke Version]", "popularity": 0, "preview_url": null, "track_number": 10, "type": "track", "uri": "spotify:track:2V5e8ubNeF9i24Uy1jaDLP"}, "artist_data": [{"external_urls": {"spotify": "https://open.spotify.com/artist/3JoDcjZtpq0ccldFgYmeAB"}, "href": "https://api.spotify.com/v1/artists/3JoDcjZtpq0ccldFgYmeAB", "id": "3JoDcjZtpq0ccldFgYmeAB", "name": "Party Tyme Karaoke", "type": "artist", "uri": "spotify:artist:3JoDcjZtpq0ccldFgYmeAB"}], "plays": 2}